stock_functions.py
stonk.py
stonk-0.0.1.dist-info/METADATA
stonk-0.0.1.dist-info/WHEEL
stonk-0.0.1.dist-info/top_level.txt
stonk-0.0.1.dist-info/RECORD
