Metadata-Version: 2.1
Name: stonk
Version: 0.0.1
Summary: A set of tools to pull and analyze stock data.
Home-page: https://github.com/metalcorebear/stonks
Author: metalcorebear
Author-email: mark.mbailey@gmail.com
License: UNKNOWN
Platform: UNKNOWN
Classifier: Topic :: Scientific/Engineering :: Mathematics
Classifier: Topic :: Office/Business :: Financial :: Investment
Classifier: Development Status :: 1 - Planning
Classifier: Programming Language :: Python :: 3.7
Classifier: License :: OSI Approved :: MIT License
Classifier: Operating System :: OS Independent
Requires-Python: >=3.7
Requires-Dist: requests
Requires-Dist: numpy
Requires-Dist: pandas
